nacos_app/__init__.py
nacos_app/apps.py
nacos_app/balanced.py
nacos_app/obj.py
nacos_app/register.py
nacos_app/service.py
nacos_app/util.py
nacos_app-1.1.4.dist-info/METADATA
nacos_app-1.1.4.dist-info/WHEEL
nacos_app-1.1.4.dist-info/top_level.txt
nacos_app-1.1.4.dist-info/RECORD
