Metadata-Version: 2.1
Name: nacos-app
Version: 1.1.4
Summary: django-nacos-app
Home-page: UNKNOWN
Author: 徐益庆
Author-email: 1593134926@qq.com
License: UNKNOWN
Platform: UNKNOWN
Requires-Python: >=2.6, !=3.0.*, !=3.1.*, !=3.2.*, <4
